django_expvar_psutil-0.1.0.dist-info/DESCRIPTION.rst
django_expvar_psutil-0.1.0.dist-info/METADATA
django_expvar_psutil-0.1.0.dist-info/RECORD
django_expvar_psutil-0.1.0.dist-info/WHEEL
django_expvar_psutil-0.1.0.dist-info/metadata.json
django_expvar_psutil-0.1.0.dist-info/top_level.txt
expvarpsutil/__init__.py
expvarpsutil/__init__.pyc
expvarpsutil/models.py
expvarpsutil/models.pyc
expvarpsutil/vars.py
expvarpsutil/vars.pyc
