Metadata-Version: 2.0
Name: django-expvar-psutil
Version: 0.1.0
Summary: Django expvar endpoint psutil plugin
Home-page: https://github.com/thraxil/django-expvar-psutil
Author: Anders Pearson
Author-email: anders@columbia.edu
License: BSD
Platform: any
Requires-Dist: Django (>=1.8)
Requires-Dist: django-expvar
Requires-Dist: nose
Requires-Dist: psutil
Requires-Dist: six
